LICENSE
MANIFEST.in
README.rst
setup.py
gglsbl3/MalwarePatternType_pb2.py
gglsbl3/__init__.py
gglsbl3/client.py
gglsbl3/protobuf_pb2.py
gglsbl3/protocol.py
gglsbl3/storage.py
gglsbl3.egg-info/PKG-INFO
gglsbl3.egg-info/SOURCES.txt
gglsbl3.egg-info/dependency_links.txt
gglsbl3.egg-info/requires.txt
gglsbl3.egg-info/top_level.txt
gglsbl3/util/__init__.py
gglsbl3/util/format_utils.py
gglsbl3/util/network_utils.py
scripts/gglsbl_client.py