Metadata-Version: 1.1
Name: gglsbl3
Version: 0.1.4
Summary: Client library for Google Safe Browsing API
Home-page: https://github.com/Stefan-Code/gglsbl3
Author: Stefan Kuntz
Author-email: Stefan.github@gmail.com
License: Apache2
Keywords: gglsbl3 gglsbl safebrowsing google-safe-browing googlesafebrowsing
Platform: UNKNOWN
Classifier: Programming Language :: Python :: 3
Classifier: Programming Language :: Python :: 3.3
Classifier: Programming Language :: Python :: 3.4
Classifier: Programming Language :: Python :: 3.5
Classifier: Programming Language :: Python :: Implementation :: CPython
Classifier: Intended Audience :: Developers
Classifier: Topic :: Internet
Classifier: Topic :: Software Development :: Libraries :: Python Modules
